setup.cfg
setup.py
metaconfig/__init__.py
metaconfig/decorator.py
metaconfig/mconf.py
metaconfig.egg-info/PKG-INFO
metaconfig.egg-info/SOURCES.txt
metaconfig.egg-info/dependency_links.txt
metaconfig.egg-info/entry_points.txt
metaconfig.egg-info/not-zip-safe
metaconfig.egg-info/top_level.txt
test/test_decorators.py
test/test_global.py
test/test_metaconfig.py