Metadata-Version: 1.1
Name: metaconfig
Version: 0.1.4
Summary: A ConfigParser bootstraping library
Home-page: UNKNOWN
Author: Stephen Pascoe
Author-email: Stephen.Pascoe@stfc.ac.uk
License: BSD
Download-URL: http://ndg.nerc.ac.uk/dist
Platform: UNKNOWN
Classifier: Development Status :: 3 - Alpha
Classifier: License :: OSI Approved :: BSD License
Classifier: Topic :: Software Development :: Libraries
